CHANGELOG.md
enex2notion/__init__.py
enex2notion/__main__.py
enex2notion/cli.py
enex2notion/cli_args.py
enex2notion/cli_logging.py
enex2notion/cli_notion.py
enex2notion/cli_upload.py
enex2notion/cli_wkhtmltopdf.py
enex2notion/enex_parser.py
enex2notion/enex_parser_xml.py
enex2notion/enex_types.py
enex2notion/enex_uploader.py
enex2notion/enex_uploader_block.py
enex2notion/enex_uploader_modes.py
enex2notion/note_parser/__init__.py
enex2notion/note_parser/blocks.py
enex2notion/note_parser/blocks_helpers.py
enex2notion/note_parser/blocks_indented.py
enex2notion/note_parser/elements/__init__.py
enex2notion/note_parser/elements/div.py
enex2notion/note_parser/elements/encrypt.py
enex2notion/note_parser/elements/header.py
enex2notion/note_parser/elements/list.py
enex2notion/note_parser/elements/media.py
enex2notion/note_parser/elements/table.py
enex2notion/note_parser/note.py
enex2notion/note_parser/note_post_process_condense.py
enex2notion/note_parser/note_post_process_resources.py
enex2notion/note_parser/note_type_based.py
enex2notion/note_parser/string_extractor.py
enex2notion/note_parser/string_extractor_properties.py
enex2notion/note_parser/string_extractor_split_tag.py
enex2notion/note_parser/webclip.py
enex2notion/note_parser/webclip_pdf.py
enex2notion/note_parser/webclip_stages_cleanup.py
enex2notion/note_parser/webclip_stages_common.py
enex2notion/note_parser/webclip_stages_convert.py
enex2notion/note_parser/webclip_stages_flatten.py
enex2notion/note_parser/webclip_stages_preparation.py
enex2notion/notion_blocks/__init__.py
enex2notion/notion_blocks/base.py
enex2notion/notion_blocks/container.py
enex2notion/notion_blocks/embeddable.py
enex2notion/notion_blocks/header.py
enex2notion/notion_blocks/list.py
enex2notion/notion_blocks/minor.py
enex2notion/notion_blocks/table.py
enex2notion/notion_blocks/text.py
enex2notion/notion_blocks/uploadable.py
enex2notion/utils_colors.py
enex2notion/utils_exceptions.py
enex2notion/utils_notion_filetypes.py
enex2notion-0.3.1.dist-info/LICENSE
enex2notion-0.3.1.dist-info/METADATA
enex2notion-0.3.1.dist-info/WHEEL
enex2notion-0.3.1.dist-info/entry_points.txt
enex2notion-0.3.1.dist-info/RECORD
