Metadata-Version: 2.1
Name: enex2notion
Version: 0.3.1
Summary: Import Evernote ENEX files to Notion
Home-page: https://github.com/vzhd1701/enex2notion
License: MIT
Keywords: evernote,enex,notion,import
Author: vzhd1701
Author-email: vzhd1701@gmail.com
Requires-Python: >=3.8,<4.0
Classifier: Development Status :: 4 - Beta
Classifier: Environment :: Console
Classifier: Intended Audience :: End Users/Desktop
Classifier: License :: OSI Approved :: MIT License
Classifier: Natural Language :: English
Classifier: Operating System :: MacOS
Classifier: Operating System :: Microsoft
Classifier: Operating System :: Unix
Classifier: Programming Language :: Python :: 3
Classifier: Programming Language :: Python :: 3.8
Classifier: Programming Language :: Python :: 3.9
Classifier: Programming Language :: Python :: 3.10
Classifier: Programming Language :: Python :: 3.11
Classifier: Topic :: Internet
Classifier: Topic :: Terminals
Classifier: Topic :: Utilities
Requires-Dist: PyMuPDF (>=1.23.5,<2.0.0)
Requires-Dist: beautifulsoup4 (>=4.12.2,<5.0.0)
Requires-Dist: lxml (>=4.9.3,<5.0.0)
Requires-Dist: notion-vzhd1701-fork (==0.0.37)
Requires-Dist: pdfkit (>=1.0.0,<2.0.0)
Requires-Dist: python-dateutil (>=2.8.2,<3.0.0)
Requires-Dist: requests (>=2.31.0,<3.0.0)
Requires-Dist: tinycss2 (>=1.2.1,<2.0.0)
Requires-Dist: tqdm (>=4.66.1,<5.0.0)
Requires-Dist: w3lib (>=2.1.2,<3.0.0)
Project-URL: Changelog, https://github.com/vzhd1701/enex2notion/blob/master/CHANGELOG.md
Project-URL: Repository, https://github.com/vzhd1701/enex2notion
